Metadata-Version: 2.1
Name: vicolib
Version: 0.0.2
Summary: Vicos python library with useful decorators and functions.
Home-page: https://github.com/VicoShortman/vico-lib-py
Author: Vico Shortman
Author-email: vico.shortman@gmail.com
License: MIT
Keywords: tools,time,timestamp,conversion,decorators,benchmark
Classifier: Development Status :: 5 - Production/Stable
Classifier: Intended Audience :: Developers
Classifier: Operating System :: OS Independent
Classifier: License :: OSI Approved :: MIT License
Classifier: Programming Language :: Python :: 3
License-File: LICENCE.txt
